lpdr/__init__.py
lpdr/lpdr.py
lpdr/wpod_net/wpod_net_update1.h5
lpdr/wpod_net/wpod_net_update1.json
lpdr-0.1.data/data/lpdr/wpod_net/wpod_net_update1.h5
lpdr-0.1.data/data/lpdr/wpod_net/wpod_net_update1.json
lpdr-0.1.dist-info/LICENSE
lpdr-0.1.dist-info/METADATA
lpdr-0.1.dist-info/WHEEL
lpdr-0.1.dist-info/top_level.txt
lpdr-0.1.dist-info/RECORD
