Metadata-Version: 2.1
Name: lpdr
Version: 0.1
Summary: License Plate Detector and Recognizer
Home-page: https://github.com/szachovy/lpdr
Author: Wiktor Maj
Author-email: wjmaj98@gmail.com
License: MIT
Platform: UNKNOWN
Classifier: License :: OSI Approved :: MIT License
Classifier: Development Status :: 4 - Beta
Classifier: Intended Audience :: Science/Research
Classifier: Programming Language :: Python :: 3
Requires-Dist: numpy (>=1.17.4)
Requires-Dist: opencv-python (==4.1.2.30)
Requires-Dist: Keras (>=2.3.1)
Requires-Dist: pytesseract (>=0.3.4)
